aicore/__init__.py
aicore/config.py
aicore/const.py
aicore/logger.py
aicore/models.py
aicore/models_metadata.json
aicore/models_metadata.py
aicore/utils.py
aicore/embeddings/__init__.py
aicore/embeddings/config.py
aicore/embeddings/embeddings.py
aicore/embeddings/providers/__init__.py
aicore/embeddings/providers/base_provider.py
aicore/embeddings/providers/gemini.py
aicore/embeddings/providers/groq.py
aicore/embeddings/providers/mistral.py
aicore/embeddings/providers/nvidia.py
aicore/embeddings/providers/openai.py
aicore/llm/__init__.py
aicore/llm/config.py
aicore/llm/llm.py
aicore/llm/templates.py
aicore/llm/usage.py
aicore/llm/utils.py
aicore/llm/mcp/__init__.py
aicore/llm/mcp/client.py
aicore/llm/mcp/models.py
aicore/llm/mcp/utils.py
aicore/llm/providers/__init__.py
aicore/llm/providers/base_provider.py
aicore/llm/providers/deepseek.py
aicore/llm/providers/gemini.py
aicore/llm/providers/grok.py
aicore/llm/providers/groq.py
aicore/llm/providers/mistral.py
aicore/llm/providers/nvidia.py
aicore/llm/providers/openai.py
aicore/llm/providers/openrouter.py
aicore/llm/providers/zai.py
aicore/llm/providers/anthropic/__init__.py
aicore/llm/providers/anthropic/consts.py
aicore/llm/providers/anthropic/oauth.py
aicore/observability/__init__.py
aicore/observability/collector.py
aicore/observability/dashboard.py
aicore/observability/models.py
aicore/observability/utils.py
aicore/observability/assets/favicon.ico
aicore/observability/assets/styles.css
core_for_ai-0.2.254.dist-info/licenses/LICENSE
core_for_ai-0.2.254.dist-info/METADATA
core_for_ai-0.2.254.dist-info/WHEEL
core_for_ai-0.2.254.dist-info/top_level.txt
core_for_ai-0.2.254.dist-info/RECORD
