Metadata-Version: 2.4
Name: core-for-ai
Version: 0.2.254
Summary: A unified interface for interacting with various LLM and embedding providers, with observability tools.
Home-page: https://github.com/BrunoV21/AiCore
Author: Bruno V.
Author-email: bruno.vitorino@tecnico.ulisboa.pt
Classifier: Programming Language :: Python :: 3.11
Classifier: Programming Language :: Python :: 3.12
Classifier: Programming Language :: Python :: 3.13
Classifier: License :: OSI Approved :: Apache Software License
Classifier: Operating System :: OS Independent
License-File: LICENSE
Requires-Dist: anthropic==0.52.0
Requires-Dist: google-genai==1.38.0
Requires-Dist: groq==0.31.0
Requires-Dist: fastmcp>=2.2.6
Requires-Dist: mistralai==1.7.0
Requires-Dist: loguru>=0.7.3
Requires-Dist: openai>=1.75.0
Requires-Dist: tenacity==9.0.0
Requires-Dist: deepseek-tokenizer==0.1.3
Requires-Dist: tiktoken==0.9.0
Requires-Dist: pydantic>=2.10.3
Requires-Dist: pytest==8.3.4
Requires-Dist: pytest-asyncio==0.25.2
Requires-Dist: PyYAML==6.0.2
Requires-Dist: python-dateutil==2.9.0
Requires-Dist: setuptools==78.1.1
Requires-Dist: json_repair==0.35.0
Requires-Dist: pytz==2025.2
Requires-Dist: ulid==1.1
Provides-Extra: dashboard
Requires-Dist: dash==2.18.2; extra == "dashboard"
Requires-Dist: dash_bootstrap_components==1.7.1; extra == "dashboard"
Requires-Dist: pandas==2.3.1; extra == "dashboard"
Requires-Dist: plotly==5.18.0; extra == "dashboard"
Requires-Dist: polars==1.24.0; extra == "dashboard"
Requires-Dist: pyarrow==19.0.1; extra == "dashboard"
Requires-Dist: aiofiles>=23.2.1; extra == "dashboard"
Requires-Dist: orjson>=3.11.1; extra == "dashboard"
Provides-Extra: sql
Requires-Dist: aioodbc==0.5.0; extra == "sql"
Requires-Dist: asyncpg==0.30.0; extra == "sql"
Requires-Dist: greenlet>=3.1.1; extra == "sql"
Requires-Dist: psycopg2==2.9.10; extra == "sql"
Requires-Dist: pyodbc==5.2.0; extra == "sql"
Requires-Dist: python-dotenv>=1.1.0; extra == "sql"
Requires-Dist: SQLAlchemy==2.0.36; extra == "sql"
Provides-Extra: all
Requires-Dist: SQLAlchemy==2.0.36; extra == "all"
Requires-Dist: aiofiles>=23.2.1; extra == "all"
Requires-Dist: aioodbc==0.5.0; extra == "all"
Requires-Dist: asyncpg==0.30.0; extra == "all"
Requires-Dist: dash==2.18.2; extra == "all"
Requires-Dist: dash_bootstrap_components==1.7.1; extra == "all"
Requires-Dist: greenlet>=3.1.1; extra == "all"
Requires-Dist: orjson>=3.11.1; extra == "all"
Requires-Dist: pandas==2.3.1; extra == "all"
Requires-Dist: plotly==5.18.0; extra == "all"
Requires-Dist: polars==1.24.0; extra == "all"
Requires-Dist: psycopg2==2.9.10; extra == "all"
Requires-Dist: pyarrow==19.0.1; extra == "all"
Requires-Dist: pyodbc==5.2.0; extra == "all"
Requires-Dist: python-dotenv>=1.1.0; extra == "all"
Dynamic: author
Dynamic: author-email
Dynamic: classifier
Dynamic: description
Dynamic: description-content-type
Dynamic: home-page
Dynamic: license-file
Dynamic: provides-extra
Dynamic: requires-dist
Dynamic: summary
